kangry_pomodoro/__init__.py
kangry_pomodoro/app.py
kangry_pomodoro/pomodoro_timer.py
kangry_pomodoro/trayicon.py
static/icon.png
kangry_pomodoro-0.1.1.dist-info/entry_points.txt
kangry_pomodoro-0.1.1.dist-info/WHEEL
kangry_pomodoro-0.1.1.dist-info/METADATA
kangry_pomodoro-0.1.1.dist-info/RECORD
