Metadata-Version: 2.1
Name: kangry-pomodoro
Version: 0.1.1
Summary: 
Author: Gregory
Author-email: netsafe.g@gmail.com
Requires-Python: >=3.7,<4.0
Classifier: Programming Language :: Python :: 3
Classifier: Programming Language :: Python :: 3.7
Classifier: Programming Language :: Python :: 3.8
Requires-Dist: click (>=7.0,<8.0)
Requires-Dist: dbus-python (>=1.2,<2.0)
Requires-Dist: notify2 (>=0.3.1,<0.4.0)
Requires-Dist: pyqt5 (>=5.13,<6.0)
